{"reviews": {"185975141": {"recommendationid": "185975141", "author": {"steamid": "76561199077450545", "num_games_owned": 0, "num_reviews": 1, "playtime_forever": 1184, "playtime_last_two_weeks": 98, "playtime_at_review": 1184, "last_played": 1737322461}, "language": "spanish", "review": "Que vuelva por fa.", "timestamp_created": 1737324007, "timestamp_updated": 1737324007, "voted_up": true, "votes_up": 1, "votes_funny": 0, "weighted_vote_score": "0.523809552192687988", "comment_count": 0, "steam_purchase": false, "received_for_free": false, "written_during_early_access": false, "primarily_steam_deck": false}, "185547195": {"recommendationid": "185547195", "author": {"steamid": "76561198413539073", "num_games_owned": 102, "num_reviews": 7, "playtime_forever": 33, "playtime_last_two_weeks": 0, "playtime_at_review": 33, "last_played": 1557689889}, "language": "english", "review": "One of the best games of all time.", "timestamp_created": 1736816853, "timestamp_updated": 1736816853, "voted_up": true, "votes_up": 0, "votes_funny": 0, "weighted_vote_score": 0, "comment_count": 0, "steam_purchase": false, "received_for_free": false, "written_during_early_access": false, "primarily_steam_deck": false}, "185500435": {"recommendationid": "185500435", "author": {"steamid": "76561198195229343", "num_games_owned": 1748, "num_reviews": 89, "playtime_forever": 89, "playtime_last_two_weeks": 0, "playtime_at_review": 89, "last_played": 1484034673}, "language": "english", "review": "Give us this back", "timestamp_created": 1736759827, "timestamp_updated": 1736759827, "voted_up": true, "votes_up": 0, "votes_funny": 0, "weighted_vote_score": 0, "comment_count": 0, "steam_purchase": false, "received_for_free": false, "written_during_early_access": false, "primarily_steam_deck": false}, "185469874": {"recommendationid": "185469874", "author": {"steamid": "76561198077964885", "num_games_owned": 0, "num_reviews": 2, "playtime_forever": 193, "playtime_last_two_weeks": 0, "playtime_at_review": 193, "last_played": 1355212800}, "language": "brazilian", "review": "S\u00f3 queria que esse jogo voltasse a esta dison\u00edvel para ser jogado, cresci jogando esse game e era incrivel jogar, podia ter seus defeitos, mas era muito divertido", "timestamp_created": 1736716555, "timestamp_updated": 1736716555, "voted_up": true, "votes_up": 0, "votes_funny": 0, "weighted_vote_score": 0, "comment_count": 0, "steam_purchase": false, "received_for_free": false, "written_during_early_access": false, "primarily_steam_deck": false}, "185451848": {"recommendationid": "185451848", "author": {"steamid": "76561198869917359", "num_games_owned": 0, "num_reviews": 35, "playtime_forever": 740, "playtime_last_two_weeks": 0, "playtime_at_review": 740, "last_played": 1594817023}, "language": "english", "review": "When I first played this game it kind of reminded me of team fortress 2 but with dc characters. I miss the game so much. Rest In Piece Gotham City Impostors.", "timestamp_created": 1736700621, "timestamp_updated": 1736700621, "voted_up": true, "votes_up": 0, "votes_funny": 0, "weighted_vote_score": 0, "comment_count": 0, "steam_purchase": false, "received_for_free": false, "written_during_early_access": false, "primarily_steam_deck": false}, "185385109": {"recommendationid": "185385109", "author": {"steamid": "76561198090509314", "num_games_owned": 0, "num_reviews": 3, "playtime_forever": 228, "playtime_last_two_weeks": 0, "playtime_at_review": 228, "last_played": 1383318014}, "language": "english", "review": " forgot this game existed", "timestamp_created": 1736630896, "timestamp_updated": 1736630896, "voted_up": true, "votes_up": 0, "votes_funny": 0, "weighted_vote_score": 0, "comment_count": 0, "steam_purchase": false, "received_for_free": false, "written_during_early_access": false, "primarily_steam_deck": false}, "185377149": {"recommendationid": "185377149", "author": {"steamid": "76561198067019857", "num_games_owned": 0, "num_reviews": 3, "playtime_forever": 13, "playtime_last_two_weeks": 0, "playtime_at_review": 13, "last_played": 1530672051}, "language": "french", "review": "come back pls :(", "timestamp_created": 1736624422, "timestamp_updated": 1736624422, "voted_up": true, "votes_up": 1, "votes_funny": 0, "weighted_vote_score": "0.523809552192687988", "comment_count": 0, "steam_purchase": false, "received_for_free": false, "written_during_early_access": false, "primarily_steam_deck": false}, "184890063": {"recommendationid": "184890063", "author": {"steamid": "76561198163092124", "num_games_owned": 335, "num_reviews": 53, "playtime_forever": 48, "playtime_last_two_weeks": 0, "playtime_at_review": 48, "last_played": 1595259548}, "language": "english", "review": "i played this game mostly on xbox when i was younger, sucks to see they gave up immediately", "timestamp_created": 1736127969, "timestamp_updated": 1736127969, "voted_up": true, "votes_up": 0, "votes_funny": 0, "weighted_vote_score": 0, "comment_count": 0, "steam_purchase": false, "received_for_free": true, "written_during_early_access": false, "primarily_steam_deck": false}, "184570521": {"recommendationid": "184570521", "author": {"steamid": "76561198263352789", "num_games_owned": 176, "num_reviews": 6, "playtime_forever": 22, "playtime_last_two_weeks": 0, "playtime_at_review": 22, "last_played": 1714368628}, "language": "english", "review": "No game will ever compare to you.... I spent HUNDREDS of hours on this game on xbox 360 and there was NOTHING like it on the market. I wish this game would come back but I guess all we have is this memorial page of it RIP to one of the best FPS games i've ever played in my life. You will be missed but never forgotten <3", "timestamp_created": 1735854040, "timestamp_updated": 1735854040, "voted_up": true, "votes_up": 0, "votes_funny": 0, "weighted_vote_score": 0, "comment_count": 0, "steam_purchase": false, "received_for_free": true, "written_during_early_access": false, "primarily_steam_deck": false}, "184532135": {"recommendationid": "184532135", "author": {"steamid": "76561198183226589", "num_games_owned": 0, "num_reviews": 10, "playtime_forever": 17, "playtime_last_two_weeks": 0, "playtime_at_review": 17, "last_played": 1452957498}, "language": "russian", "review": "R.I.P.", "timestamp_created": 1735826618, "timestamp_updated": 1735826618, "voted_up": true, "votes_up": 0, "votes_funny": 0, "weighted_vote_score": 0, "comment_count": 0, "steam_purchase": false, "received_for_free": false, "written_during_early_access": false, "primarily_steam_deck": false}, "184488805": {"recommendationid": "184488805", "author": {"steamid": "76561198217688432", "num_games_owned": 226, "num_reviews": 65, "playtime_forever": 271, "playtime_last_two_weeks": 0, "playtime_at_review": 271, "last_played": 1624764152}, "language": "english", "review": "Thinking of you... used to play all the time on the ps3 before finding it on steam", "timestamp_created": 1735783597, "timestamp_updated": 1735783597, "voted_up": true, "votes_up": 0, "votes_funny": 0, "weighted_vote_score": 0, "comment_count": 0, "steam_purchase": false, "received_for_free": false, "written_during_early_access": false, "primarily_steam_deck": false}, "184272428": {"recommendationid": "184272428", "author": {"steamid": "76561198973338743", "num_games_owned": 0, "num_reviews": 2, "playtime_forever": 29, "playtime_last_two_weeks": 0, "playtime_at_review": 29, "last_played": 1659391887}, "language": "english", "review": "i miss you everyday", "timestamp_created": 1735605648, "timestamp_updated": 1735605648, "voted_up": true, "votes_up": 2, "votes_funny": 0, "weighted_vote_score": "0.53125", "comment_count": 0, "steam_purchase": false, "received_for_free": false, "written_during_early_access": false, "primarily_steam_deck": false}, "184180127": {"recommendationid": "184180127", "author": {"steamid": "76561198332772349", "num_games_owned": 0, "num_reviews": 34, "playtime_forever": 100, "playtime_last_two_weeks": 0, "playtime_at_review": 100, "last_played": 1509197788}, "language": "russian", "review": "\u0412\u0440\u043e\u0434\u0435 \u043d\u043e\u0440\u043c \u0438\u0433\u0440\u0430. \u041e\u0447\u0435\u043d\u044c \u0440\u0430\u0437\u043d\u043e\u043e\u0431\u0440\u0430\u0437\u043d\u043e \u0438 \u0432\u0435\u0441\u0435\u043b\u043e :)\n", "timestamp_created": 1735527411, "timestamp_updated": 1735527503, "voted_up": true, "votes_up": 1, "votes_funny": 0, "weighted_vote_score": "0.523809552192687988", "comment_count": 0, "steam_purchase": false, "received_for_free": false, "written_during_early_access": false, "primarily_steam_deck": false}, "184177566": {"recommendationid": "184177566", "author": {"steamid": "76561198083757591", "num_games_owned": 0, "num_reviews": 26, "playtime_forever": 354, "playtime_last_two_weeks": 0, "playtime_at_review": 354, "last_played": 1370792072}, "language": "english", "review": "Miss this game", "timestamp_created": 1735525095, "timestamp_updated": 1735525095, "voted_up": true, "votes_up": 1, "votes_funny": 0, "weighted_vote_score": "0.508196711540222168", "comment_count": 0, "steam_purchase": false, "received_for_free": false, "written_during_early_access": false, "primarily_steam_deck": false}, "183984010": {"recommendationid": "183984010", "author": {"steamid": "76561198052758054", "num_games_owned": 324, "num_reviews": 17, "playtime_forever": 13, "playtime_last_two_weeks": 0, "playtime_at_review": 13, "last_played": 1346482800}, "language": "english", "review": "This was a absolute blast to play wehen it was available\n", "timestamp_created": 1735390146, "timestamp_updated": 1735390146, "voted_up": true, "votes_up": 2, "votes_funny": 0, "weighted_vote_score": "0.523809552192687988", "comment_count": 0, "steam_purchase": false, "received_for_free": false, "written_during_early_access": false, "primarily_steam_deck": false}, "183541202": {"recommendationid": "183541202", "author": {"steamid": "76561198119425188", "num_games_owned": 366, "num_reviews": 49, "playtime_forever": 2273, "playtime_last_two_weeks": 0, "playtime_at_review": 2273, "last_played": 1586497528}, "language": "english", "review": "it was alright aside from how evil the netcode was and how easy it was to get screwed over by someone with an aimbot. But since it came back recently through a revival project I've re-learnt why I stuck around longer than an hour in such a game.", "timestamp_created": 1735018876, "timestamp_updated": 1735018876, "voted_up": true, "votes_up": 0, "votes_funny": 0, "weighted_vote_score": 0, "comment_count": 0, "steam_purchase": false, "received_for_free": false, "written_during_early_access": false, "primarily_steam_deck": false}}, "query_summary": {"num_reviews": 100, "review_score": 8, "review_score_desc": "Very Positive", "total_positive": 10278, "total_negative": 1765, "total_reviews": 12043}, "cursors": {"AoJww9vDyI4DeZ2r6QQ=": "Mon Jan 20 15:57:38 2025"}}
