{"reviews": {"184953029": {"recommendationid": "184953029", "author": {"steamid": "76561198096938329", "num_games_owned": 0, "num_reviews": 323, "playtime_forever": 188, "playtime_last_two_weeks": 0, "playtime_at_review": 188, "last_played": 1736188297}, "language": "english", "review": "Played it in 2021, but today I logged in bc I was missing an achievement, and it reminded me how bad the dialogues are.", "timestamp_created": 1736189090, "timestamp_updated": 1736189090, "voted_up": false, "votes_up": 0, "votes_funny": 0, "weighted_vote_score": 0, "comment_count": 0, "steam_purchase": true, "received_for_free": false, "written_during_early_access": false, "primarily_steam_deck": false}}, "query_summary": {"num_reviews": 100, "review_score": 8, "review_score_desc": "Very Positive", "total_positive": 191, "total_negative": 43, "total_reviews": 234}, "cursors": {"AoJ4z4aUp9sCdeaqdg==": "Mon Jan 20 19:50:01 2025"}}
